agentgrunt/gpt_tools/README_ai.md
agentgrunt/gpt_tools/code_exploration.py
agentgrunt/gpt_tools/code_exploration_docs.md
agentgrunt/main.py
agentgrunt/repo_mgmt.py
agentgrunt/utils.py
agentgrunt-0.1.5.dist-info/METADATA
agentgrunt-0.1.5.dist-info/WHEEL
agentgrunt-0.1.5.dist-info/entry_points.txt
agentgrunt-0.1.5.dist-info/RECORD
