Metadata-Version: 2.1
Name: agentgrunt
Version: 0.1.5
Summary: 
License: MIT
Author: Nik V
Author-email: github@nikvdp.com
Requires-Python: >=3.9
Classifier: License :: OSI Approved :: MIT License
Classifier: Programming Language :: Python :: 3
Classifier: Programming Language :: Python :: 3.9
Classifier: Programming Language :: Python :: 3.10
Classifier: Programming Language :: Python :: 3.11
Requires-Dist: httpx (>=0.24.1,<0.25.0)
Requires-Dist: plumbum (>=1.8.2,<2.0.0)
Requires-Dist: pydantic (>=2.1.1,<3.0.0)
Requires-Dist: tqdm (>=4.65.0,<5.0.0)
Requires-Dist: typer (>=0.9.0,<0.10.0)
